{
  "slug": "huxley-soma-1932",
  "text": "A really efficient totalitarian state would be one in which the all-powerful executive of political bosses and their army of managers control a population of slaves who do not have to be coerced, because they love their servitude.",
  "author": "Aldous Huxley",
  "authorSlug": "aldous-huxley",
  "source": "Brave New World, foreword to 1946 edition (novel published 1932)",
  "yearWritten": 1946,
  "yearImagined": "distant future",
  "categories": [
    "Society",
    "War & Politics",
    "Technology"
  ],
  "didItHoldUp": {
    "verdict": "partially-true",
    "analysis": "Huxley's dystopia looks more prescient than Orwell's with each passing year. We weren't subdued by force — we were pacified by entertainment, convenience, and dopamine hits from social media. Infinite content streams, algorithmically optimized to hold attention, function remarkably like soma. The coercion Huxley feared isn't absent, but it's subtle: we surrender privacy and autonomy not because we're forced to, but because the alternative is inconvenient. We don't love our servitude exactly — but we do keep scrolling."
  },
  "quoteSource": "ai-generated",
  "status": "published"
}
