{
  "slug": "padmanabhan-harvest-donor-world-1997",
  "text": "Time: The year is 2010. There are significant technical advances, but the clothes and habits of ordinary people in the 'Donor' World are no different to those of Third World citizens today.",
  "author": "Manjula Padmanabhan",
  "authorSlug": "manjula-padmanabhan",
  "source": "Harvest, Kali for Women, 1997. Winner of 1997 Onassis Award.",
  "yearWritten": 1997,
  "yearImagined": "2010",
  "categories": [
    "Society",
    "Health & Medicine",
    "Technology"
  ],
  "didItHoldUp": {
    "verdict": "true",
    "analysis": "By 2010, Mumbai's reality eerily mirrored Padmanabhan's dystopia. India's organ trafficking crisis was extensively documented, with impoverished donors selling kidneys to wealthy recipients — both domestic and international. Smartphone adoption was exploding, video calling had become commonplace, yet the rich-poor divide remained exactly as depicted. The play's core premise — that globalization would create a world where the poor literally sell their bodies to the rich, mediated by technology — proved disturbingly accurate."
  },
  "quoteSource": "ai-generated",
  "status": "published"
}
